aniquote/__init__.py
aniquote/quotes.py
aniquote-1.0.0.dist-info/License.txt
aniquote-1.0.0.dist-info/METADATA
aniquote-1.0.0.dist-info/WHEEL
aniquote-1.0.0.dist-info/entry_points.txt
aniquote-1.0.0.dist-info/top_level.txt
aniquote-1.0.0.dist-info/RECORD
