Metadata-Version: 2.1
Name: aniquote
Version: 1.0.0
Summary: A Python package to generate famous quotes from various anime characters.
Home-page: https://github.com/MandarKelkarOfficial/aniquotes.git
Author: Mandar Kelkar
Author-email: mandarkelkarofficial@gmail.com
License: MIT
Keywords: anime quotes character famous
Classifier: Development Status :: 5 - Production/Stable
Classifier: Intended Audience :: Developers
Classifier: License :: OSI Approved :: MIT License
Classifier: Programming Language :: Python :: 3
Classifier: Programming Language :: Python :: 3.6
Classifier: Programming Language :: Python :: 3.7
Classifier: Programming Language :: Python :: 3.8
Classifier: Programming Language :: Python :: 3.9
Requires-Python: >= 3.6
License-File: License.txt
